momba_engine-0.6.12.dist-info/METADATA
momba_engine-0.6.12.dist-info/WHEEL
momba_engine/__init__.py
momba_engine/momba_engine.abi3.so
momba_engine-0.6.12.dist-info/RECORD
