Metadata-Version: 2.3
Name: momba_engine
Version: 0.6.12
Summary: Momba's state space exploration engine.
Author: Maximilian Köhl <koehl@cs.uni-saarland.de>
Author-email: Maximilian Köhl <koehl@cs.uni-saarland.de>
License: MIT OR Apache-2.0
Requires-Python: >=3.8
Project-URL: Source Code, https://github.com/koehlma/momba
